codebase_token_counter/__init__.py
codebase_token_counter/__main__.py
codebase_token_counter/token_counter.py
tests/__init__.py
tests/test_repository.py
tests/test_token_counter.py
code_token_counter-0.1.2.dist-info/METADATA
code_token_counter-0.1.2.dist-info/WHEEL
code_token_counter-0.1.2.dist-info/entry_points.txt
code_token_counter-0.1.2.dist-info/top_level.txt
code_token_counter-0.1.2.dist-info/RECORD
