Metadata-Version: 2.4
Name: code-token-counter
Version: 0.1.2
Summary: A tool to count tokens in your codebase
Home-page: https://github.com/Xytronix/codebase-token-counter
Author: Liatrio
Classifier: Development Status :: 3 - Alpha
Classifier: Intended Audience :: Developers
Classifier: License :: OSI Approved :: MIT License
Classifier: Operating System :: OS Independent
Classifier: Programming Language :: Python :: 3
Classifier: Programming Language :: Python :: 3.8
Classifier: Programming Language :: Python :: 3.9
Classifier: Programming Language :: Python :: 3.10
Classifier: Programming Language :: Python :: 3.11
Requires-Python: >=3.8
Requires-Dist: gitpython==3.1.41
Requires-Dist: tqdm==4.66.3
Requires-Dist: transformers==4.38.1
Requires-Dist: rich==13.9.4
Requires-Dist: chardet
Requires-Dist: pytest==8.0.0
Requires-Dist: pytest-cov==4.1.0
Dynamic: author
Dynamic: classifier
Dynamic: description
Dynamic: description-content-type
Dynamic: home-page
Dynamic: requires-dist
Dynamic: requires-python
Dynamic: summary
